dbwipes/__init__.py
dbwipes/db.py
dbwipes/scorpionutil.py
dbwipes/server.py
dbwipes/settings.py
dbwipes/summary.py
dbwipes/util.py
dbwipes/static/base.css
dbwipes/static/css/base.css
dbwipes/static/css/base.less
dbwipes/static/css/bootstrap-slider.css
dbwipes/static/css/bootstrap-switch.css
dbwipes/static/css/bootstrap-theme.css
dbwipes/static/css/bootstrap-theme.css.map
dbwipes/static/css/bootstrap-theme.min.css
dbwipes/static/css/bootstrap.css
dbwipes/static/css/bootstrap.css.map
dbwipes/static/css/bootstrap.min.css
dbwipes/static/css/docs.min.css
dbwipes/static/css/index.html
dbwipes/static/css/shepherd-theme-arrows-plain-buttons.css
dbwipes/static/css/shepherd-theme-arrows.css
dbwipes/static/css/shepherd.css
dbwipes/static/css/tether-theme-arrows-dark.css
dbwipes/static/css/tether-theme-arrows.css
dbwipes/static/css/tether-theme-basic.css
dbwipes/static/css/tether.css
dbwipes/static/fonts/carme.css
dbwipes/static/fonts/carme.ttf
dbwipes/static/fonts/glyphicons-halflings-regular.eot
dbwipes/static/fonts/glyphicons-halflings-regular.svg
dbwipes/static/fonts/glyphicons-halflings-regular.ttf
dbwipes/static/fonts/glyphicons-halflings-regular.woff
dbwipes/static/fonts/opensans-light.css
dbwipes/static/fonts/opensans-light.ttf
dbwipes/static/images/ew-resize.gif
dbwipes/static/images/ns-resize.gif
dbwipes/static/js/base.js
dbwipes/static/js/require.js
dbwipes/static/js/summary.js
dbwipes/static/js/summarydrspott.js
dbwipes/static/js/lib/backbone.js
dbwipes/static/js/lib/bootstrap-slider.js
dbwipes/static/js/lib/bootstrap-switch.js
dbwipes/static/js/lib/bootstrap.js
dbwipes/static/js/lib/bootstrap.min.js
dbwipes/static/js/lib/chart.js
dbwipes/static/js/lib/d3.js
dbwipes/static/js/lib/date.js
dbwipes/static/js/lib/handlebars.js
dbwipes/static/js/lib/jquery-ui.js
dbwipes/static/js/lib/jquery.js
dbwipes/static/js/lib/md5.js
dbwipes/static/js/lib/shepherd.js
dbwipes/static/js/lib/sparklines.js
dbwipes/static/js/lib/tether.js
dbwipes/static/js/lib/underscore.js
dbwipes-0.0.28.dist-info/LICENSE
dbwipes-0.0.28.dist-info/METADATA
dbwipes-0.0.28.dist-info/WHEEL
dbwipes-0.0.28.dist-info/top_level.txt
dbwipes-0.0.28.dist-info/RECORD
