Metadata-Version: 2.1
Name: dbwipes
Version: 0.0.28
Summary: dbwipes a database
Home-page: http://github.com/sirrice/summary
Author: Eugene Wu
Author-email: eugenewu@mit.edu
License: MIT
Platform: UNKNOWN
Requires-Dist: flask
Requires-Dist: psycopg2
Requires-Dist: sqlalchemy
Requires-Dist: flask-compress
Requires-Dist: scorpionsql
Requires-Dist: click
Requires-Dist: bsddb3
